django_simple_pagination-1.1.8.dist-info/DESCRIPTION.rst
django_simple_pagination-1.1.8.dist-info/METADATA
django_simple_pagination-1.1.8.dist-info/RECORD
django_simple_pagination-1.1.8.dist-info/WHEEL
django_simple_pagination-1.1.8.dist-info/metadata.json
django_simple_pagination-1.1.8.dist-info/top_level.txt
simple_pagination/__init__.py
simple_pagination/admin.py
simple_pagination/models.py
simple_pagination/settings.py
simple_pagination/tests.py
simple_pagination/utils.py
simple_pagination/migrations/__init__.py
simple_pagination/templates/simple/current_link.html
simple_pagination/templates/simple/page_link.html
simple_pagination/templates/simple/show_pages.html
simple_pagination/templatetags/__init__.py
simple_pagination/templatetags/paginate.py
